{
  "words": {
    "hour": "часов",
    "half": "половина",
    "over": "после",
    "before": "до",
    "quarterOver": "четверть после",
    "quarterBefore": "без четверти"
  },
  "hours": {
    "0": "двенадцать",
    "1": "час",
    "2": "два",
    "3": "три",
    "4": "четыре",
    "5": "пять",
    "6": "шесть",
    "7": "семь",
    "8": "восемь",
    "9": "девять",
    "10": "десять",
    "11": "одиннадцать",
    "12": "двенадцать",
    "13": "тринадцать",
    "14": "четырнадцать",
    "15": "пятнадцать",
    "16": "шестнадцать",
    "17": "семнадцать",
    "18": "восемнадцать",
    "19": "девятнадцать",
    "20": "двадцать",
    "21": "двадцать один",
    "22": "двадцать два",
    "23": "двадцать три"
  },
  "minutes": {
    "1": "одна",
    "2": "две",
    "3": "три",
    "4": "четыре",
    "5": "пять",
    "6": "шесть",
    "7": "семь",
    "8": "восемь",
    "9": "девять",
    "10": "десять",
    "11": "одиннадцать",
    "12": "двенадцать",
    "13": "тринадцать",
    "14": "четырнадцать",
    "15": "четверть",
    "16": "шестнадцать",
    "17": "семнадцать",
    "18": "восемнадцать",
    "19": "девятнадцать",
    "20": "двадцать",
    "21": "двадцать одна",
    "22": "двадцать две",
    "23": "двадцать три",
    "24": "двадцать четыре",
    "25": "двадцать пять",
    "26": "двадцать шесть",
    "27": "двадцать семь",
    "28": "двадцать восемь",
    "29": "двадцать девять",
    "30": "половина"
  }
}
